Workbook

Sheet Summary
A1: Concordia University | D1: Group member names: | F1: Hugh Cronin
A2: John Molson School of Business | F2: Antonin Le Clei
A3: FINA 210 Project | F3: Abderrahmane Benchelabi
A4: Prof: Michel Deslauriers
A5: Fall 2021
A9: Summer 2021
A10: DEAL PARAMETERS | B10: Most likely | C10: Pessimistic | D10: Optimistic
A11: Asset type | B11: =+Likely!B4 -> Multi-Residential | C11: =+Pessimistic!B4 -> Multi-Residential | D11: =+Optimistic!B4 -> Multi-Residential
A12: Asking Price | B12: =+Likely!B5 -> 2685000 | C12: =+Pessimistic!B5 -> 2685000 | D12: =+Optimistic!B5 -> 2685000
A13: NOI - Year 1 | B13: =+Likely!B6 -> 118974.33 | C13: =+Pessimistic!B6 -> 116134.15 | D13: =+Optimistic!B6 -> 120940.42
A14: Implied Cap Rate | B14: =+Likely!B7 -> 0.044310739 | C14: =+Pessimistic!B7 -> 0.043252942 | D14: =+Optimistic!B7 -> 0.045042987
A15: Purchase Price | B15: =+Likely!B8 -> 2685000 | C15: =+Pessimistic!B8 -> 2695000 | D15: =+Optimistic!B8 -> 2675000
A16: Cap rate | B16: =+Likely!B9 -> 0.044310739 | C16: =+Pessimistic!B9 -> 0.043092448 | D16: =+Optimistic!B9 -> 0.045211372
A17: Financing amount | B17: =+Likely!B12 -> 1745250 | C17: =+Pessimistic!B12 -> 1617000 | D17: =+Optimistic!B12 -> 1872500
A18: Mortgage rate | B18: =+Likely!B13 -> 0.039 | C18: =+Pessimistic!B13 -> 0.042 | D18: =+Optimistic!B13 -> 0.035
A19: Mortgage amortization period | B19: =+Likely!B15 -> 25 | C19: =+Pessimistic!B15 -> 25 | D19: =+Optimistic!B15 -> 25
A20: Equity funding | B20: =+Likely!B16 -> 993450 | C20: =+Pessimistic!B16 -> 1131900 | D20: =+Optimistic!B16 -> 856000
A21: Exit cap rate | B21: =+Likely!B21 -> 0.044310739 | C21: =+Pessimistic!B21 -> 0.045 | D21: =+Optimistic!B21 -> 0.043
A22: Investor unlevered hurdle rate | B22: =+Likely!B23 -> 0.054310739 | C22: =+Pessimistic!B23 -> 0.06 | D22: =+Optimistic!B23 -> 0.063
A23: Investor levered hurdle rate | B23: =+Likely!B24 -> 0.0827 | C23: =+Pessimistic!B24 -> 0.0871 | D23: =+Optimistic!B24 -> 0.1284
A24: IRR AND NPV
A25: IRR unlevered | B25: =+Likely!B52 -> 0.071442256 | C25: =+Pessimistic!B52 -> 0.052791467 | D25: =+Optimistic!B52 -> 0.09076435
A26: NPV unlevered | B26: =+Likely!B53 -> 211475.05 | C26: =+Pessimistic!B53 -> -85013.866 | D26: =+Optimistic!B53 -> 345330.12
A27: IRR levered | B27: =+Likely!B65 -> 0.11726758 | C27: =+Pessimistic!B65 -> 0.067119595 | D27: =+Optimistic!B65 -> 0.17787468
A28: NPV levered | B28: =+Likely!B66 -> 165007.82 | C28: =+Pessimistic!B66 -> -97933.594 | D28: =+Optimistic!B66 -> 199776.09

Sheet Likely
A1: MOST LIKELY SCENARIO
A3: DEAL PARAMETERS | D3: PRI | F3: =+$B$34 -> 168096
A4: Asset type | B4: Multi-Residential | D4: Vacancy + Credit allowance | F4: =1.5%*F3 -> 2521.44
A5: Asking Price | B5: 2685000 | D5: ERI | F5: =F3-F4 -> 165574.56
A6: NOI - Year 1 | B6: =C36 -> 118974.33 | D6: Misc income | F6: 0
A7: Implied Cap rate | B7: =B6/B5 -> 0.044310739 | D7: GOI | F7: =F5 -> 165574.56
A8: Purchase Price | B8: 2685000 | D8: Operating expense | F8: =51142 -> 51142
A9: Cap rate | B9: =B6/B8 -> 0.044310739 | D9: NOI | F9: =F7-F8 -> 114432.56
A10: Acqusition expenses | B10: =0.02*B8 -> 53700
A11: Financing LTV | B11: 0.65
A12: Financing amount | B12: =B11*B8 -> 1745250
A13: Mortgage rate | B13: 0.039
A14: Mortgage monthly rate | B14: =NOMINAL(EFFECT(B13,2),12)/12 -> 0.0032239041 | E14: Weight | F14: Cost | G14: WACC
A15: Mortgage amortization period | B15: 25 | D15: Debt | E15: =B11 -> 0.65 | F15: =B13 -> 0.039
A16: Equity funding after leverage | B16: =B8-B12+B10 -> 993450 | D16: Equity | E16: =1-E15 -> 0.35 | F16: 0.0827
A17: Own Equity % | B17: 0.5 | F17: =(E15*F15)+(E16*F16) -> 0.054295 | G17: =B23 -> 0.054310739
A18: Investor Equity % | B18: 0.5
A19: Own Equity funding after leverage | B19: =B17*B16 -> 496725
A20: Investor Equity funding after leverage | B20: =B18*B16 -> 496725
A21: Exit cap rate | B21: =B7 -> 0.044310739
A22: Sale expenses | B22: 0.04 | C22: Of sale price
A23: Investor unlevered hurdle rate | B23: =B21+0.01 -> 0.054310739
A24: Investor levered hurdle rate | B24: =F16 -> 0.0827
A27: NOI AND CASH FLOW
B28: Actual | C28: Projected
B29: Last Year | C29: Year 1 | D29: Year 2 | E29: Year 3 | F29: Year 4 | G29: Year 5 | H29: Year 6
A31: Revenue growth percentage rate | C31: 0.035 | D31: 0.035 | E31: 0.035 | F31: 0.035 | G31: 0.035 | H31: 0.035
A32: Expense growth percentage rate | C32: 0.025 | D32: 0.025 | E32: 0.025 | F32: 0.025 | G32: 0.025 | H32: 0.025
A34: Revenues | B34: 168096 | C34: =+B34*(1+C31) -> 173979.36 | D34: =+C34*(1+D31) -> 180068.64 | E34: =+D34*(1+E31) -> 186371.04 | F34: =+E34*(1+F31) -> 192894.03 | G34: =+F34*(1+G31) -> 199645.32 | H34: =+G34*(1+H31) -> 206632.9
A35: Expenses | B35: =F8+F4 -> 53663.44 | C35: =+B35*(1+C32) -> 55005.026 | D35: =+C35*(1+D32) -> 56380.152 | E35: =+D35*(1+E32) -> 57789.655 | F35: =+E35*(1+F32) -> 59234.397 | G35: =+F35*(1+G32) -> 60715.257 | H35: =+G35*(1+H32) -> 62233.138
A36: NOI | B36: =B34-B35 -> 114432.56 | C36: =C34-C35 -> 118974.33 | D36: =+D34-D35 -> 123688.49 | E36: =+E34-E35 -> 128581.38 | F36: =+F34-F35 -> 133659.63 | G36: =+G34-G35 -> 138930.06 | H36: =+H34-H35 -> 144399.77
A37: Other cash flow items (if required) | B37: 0 | D37: 0 | E37: 0 | F37: 0 | G37: 0 | H37: 0
A38: Debts servicing | C38: =$C$72*12 -> -109032.04 | D38: =$C$72*12 -> -109032.04 | E38: =$C$72*12 -> -109032.04 | F38: =$C$72*12 -> -109032.04 | G38: =$C$72*12 -> -109032.04
A39: Cash flow | B39: =B36-B37+B38 -> 114432.56 | C39: =+C36-C37+C38 -> 9942.297 | D39: =+D36-D37+D38 -> 14656.449 | E39: =+E36-E37+E38 -> 19549.347 | F39: =+F36-F37+F38 -> 24627.592 | G39: =+G36-G37+G38 -> 29898.023 | H39: =+H36-H37+H38 -> 144399.77
A44: UNLEVERED CASH FLOWS
B45: Initial | C45: Year 1 | D45: Year 2 | E45: Year 3 | F45: Year 4 | G45: Year 5
A46: Investment | B46: =-B8-B10 -> -2738700
A47: Cash flow | C47: =C36-C37 -> 118974.33 | D47: =D39-D38 -> 123688.49 | E47: =E39-E38 -> 128581.38 | F47: =F39-F38 -> 133659.63 | G47: =G39-G38 -> 138930.06
A48: Cash on exit | G48: =(H36/$B$21)*(1-B22) -> 3128446.5
B49: =SUM(B46:B48) -> -2738700 | C49: =SUM(C46:C48) -> 118974.33 | D49: =SUM(D46:D48) -> 123688.49 | E49: =SUM(E46:E48) -> 128581.38 | F49: =SUM(F46:F48) -> 133659.63 | G49: =SUM(G46:G48) -> 3267376.5
A52: IRR unlevered | B52: =IRR(B49:G49) -> 0.071442256
A53: NPV unlevered | B53: =NPV(B23,C49:G49)+B49 -> 211475.05
A57: LEVERED CASH FLOWS
B58: Initial | C58: Year 1 | D58: Year 2 | E58: Year 3 | F58: Year 4 | G58: Year 5
A59: Investment | B59: =-B8-B10 -> -2738700
A60: Cash flow | B60: =B12 -> 1745250 | C60: {=C39:G39} -> 9942.297 | D60: 14656.449 | E60: 19549.347 | F60: 24627.592 | G60: 29898.023
A61: Cash on exit | G61: =((H36/B21)*(1-B22))-F131 -> 1611795.5
B62: =SUM(B59:B61) -> -993450 | C62: =SUM(C59:C61) -> 9942.297 | D62: =SUM(D59:D61) -> 14656.449 | E62: =SUM(E59:E61) -> 19549.347 | F62: =SUM(F59:F61) -> 24627.592 | G62: =SUM(G59:G61) -> 1641693.5
A65: IRR levered | B65: =IRR(B62:G62) -> 0.11726758
A66: NPV levered | B66: =NPV(B24,C62:G62)+B62 -> 165007.82
A70: DEBT AMORTIZATION SCHEDULE
A71: Payment | B71: Opening | C71: Payment | D71: Interest | E71: Capital | F71: Closing
A72: 1 | B72: =+B12 -> 1745250 | C72: =PMT($B$14,$B$15*12,B72,0) -> -9086.0031 | D72: =+B72*$B$14 -> 5626.5187 | E72: =+C72+D72 -> -3459.4844 | F72: =+B72+E72 -> 1741790.5
A73: =1+A72 -> 2 | B73: =F72 -> 1741790.5 | C73: =C72 -> -9086.0031 | D73: =+B73*$B$14 -> 5615.3657 | E73: =+C73+D73 -> -3470.6374 | F73: =+B73+E73 -> 1738319.9
A74: =1+A73 -> 3 | B74: =F73 -> 1738319.9 | C74: =C73 -> -9086.0031 | D74: =+B74*$B$14 -> 5604.1767 | E74: =+C74+D74 -> -3481.8264 | F74: =+B74+E74 -> 1734838.1
A75: =1+A74 -> 4 | B75: =F74 -> 1734838.1 | C75: =C74 -> -9086.0031 | D75: =+B75*$B$14 -> 5592.9516 | E75: =+C75+D75 -> -3493.0515 | F75: =+B75+E75 -> 1731345
A76: =1+A75 -> 5 | B76: =F75 -> 1731345 | C76: =C75 -> -9086.0031 | D76: =+B76*$B$14 -> 5581.6903 | E76: =+C76+D76 -> -3504.3128 | F76: =+B76+E76 -> 1727840.7
A77: =1+A76 -> 6 | B77: =F76 -> 1727840.7 | C77: =C76 -> -9086.0031 | D77: =+B77*$B$14 -> 5570.3927 | E77: =+C77+D77 -> -3515.6103 | F77: =+B77+E77 -> 1724325.1
A78: =1+A77 -> 7 | B78: =F77 -> 1724325.1 | C78: =C77 -> -9086.0031 | D78: =+B78*$B$14 -> 5559.0588 | E78: =+C78+D78 -> -3526.9443 | F78: =+B78+E78 -> 1720798.1
A79: =1+A78 -> 8 | B79: =F78 -> 1720798.1 | C79: =C78 -> -9086.0031 | D79: =+B79*$B$14 -> 5547.6882 | E79: =+C79+D79 -> -3538.3149 | F79: =+B79+E79 -> 1717259.8
A80: =1+A79 -> 9 | B80: =F79 -> 1717259.8 | C80: =C79 -> -9086.0031 | D80: =+B80*$B$14 -> 5536.281 | E80: =+C80+D80 -> -3549.722 | F80: =+B80+E80 -> 1713710.1
A81: =1+A80 -> 10 | B81: =F80 -> 1713710.1 | C81: =C80 -> -9086.0031 | D81: =+B81*$B$14 -> 5524.8371 | E81: =+C81+D81 -> -3561.166 | F81: =+B81+E81 -> 1710148.9
A82: =1+A81 -> 11 | B82: =F81 -> 1710148.9 | C82: =C81 -> -9086.0031 | D82: =+B82*$B$14 -> 5513.3562 | E82: =+C82+D82 -> -3572.6469 | F82: =+B82+E82 -> 1706576.3
A83: =1+A82 -> 12 | B83: =F82 -> 1706576.3 | C83: =C82 -> -9086.0031 | D83: =+B83*$B$14 -> 5501.8383 | E83: =+C83+D83 -> -3584.1647 | F83: =+B83+E83 -> 1702992.1
A84: =1+A83 -> 13 | B84: =F83 -> 1702992.1 | C84: =C83 -> -9086.0031 | D84: =+B84*$B$14 -> 5490.2833 | E84: =+C84+D84 -> -3595.7197 | F84: =+B84+E84 -> 1699396.4
... A371: =1+A370 -> 300 | B371: =F370 -> 9056.8048 | C371: =C370 -> -9086.0031 | D371: =+B371*$B$14 -> 29.198271 | E371: =+C371+D371 -> -9056.8048 | F371: =+B371+E371 -> -2.5465852e-10

Sheet Pessimistic
A1: PESSIMISTIC SCENARIO
A3: DEAL PARAMETERS | D3: PRI | F3: =+$B$34 -> 168096
A4: Asset type | B4: Multi-Residential | D4: Vacancy + Credit allowance | F4: =2.5%*F3 -> 4202.4
A5: Asking Price | B5: 2685000 | D5: ERI | F5: =F3-F4 -> 163893.6
A6: NOI - Year 1 | B6: =+C36 -> 116134.15 | D6: Misc income | F6: 0
A7: Implied Cap rate | B7: =B6/B5 -> 0.043252942 | D7: GOI | F7: =F5 -> 163893.6
A8: Purchase Price | B8: 2695000 | D8: Operating expense | F8: =51142 -> 51142
A9: Cap rate | B9: =B6/B8 -> 0.043092448 | D9: NOI | F9: =F7-F8 -> 112751.6
A10: Acqusition expenses | B10: =0.02*B8 -> 53900
A11: Financing LTV | B11: 0.6
A12: Financing amount | B12: =B11*B8 -> 1617000
A13: Mortgage rate | B13: 0.042
A14: Mortgage monthly rate | B14: =NOMINAL(EFFECT(B13,2),12)/12 -> 0.0034697623
A15: Mortgage amortization period | B15: 25 | E15: Weight | F15: Cost | G15: WACC
A16: Equity funding after leverage | B16: =B8-B12+B10 -> 1131900 | D16: Debt | E16: =B11 -> 0.6 | F16: =B13 -> 0.042
A17: Own Equity % | B17: 0.5 | D17: Equity | E17: =1-E16 -> 0.4 | F17: 0.0871
A18: Investor Equity % | B18: 0.5 | F18: =(E16*F16)+(E17*F17) -> 0.06004 | G18: 0.06
A19: Own Equity funding after leverage | B19: =B17*B16 -> 565950
A20: Investor Equity funding after leverage | B20: =B18*B16 -> 565950
A21: Exit cap rate | B21: 0.045
A22: Sale expenses | B22: 0.04 | C22: Of sale price
A23: Investor unlevered hurdle rate | B23: =B21+0.015 -> 0.06
A24: Investor levered hurdle rate | B24: =F17 -> 0.0871
A27: NOI AND CASH FLOW
B28: Actual | C28: Projected
B29: Last Year | C29: Year 1 | D29: Year 2 | E29: Year 3 | F29: Year 4 | G29: Year 5 | H29: Year 6
A31: Revenue growth percentage rate | C31: 0.03 | D31: 0.03 | E31: 0.03 | F31: 0.03 | G31: 0.03 | H31: 0.03
A32: Expense growth percentage rate | C32: 0.03 | D32: 0.03 | E32: 0.03 | F32: 0.03 | G32: 0.03 | H32: 0.03
A34: Revenues | B34: 168096 | C34: =B34*(1+C31) -> 173138.88 | D34: =C34*(1+D31) -> 178333.05 | E34: =D34*(1+E31) -> 183683.04 | F34: =E34*(1+F31) -> 189193.53 | G34: =F34*(1+G31) -> 194869.33 | H34: =G34*(1+H31) -> 200715.41
A35: Expenses | B35: =F4+F8 -> 55344.4 | C35: =B35*(1+C32) -> 57004.732 | D35: =C35*(1+D32) -> 58714.874 | E35: =D35*(1+E32) -> 60476.32 | F35: =E35*(1+F32) -> 62290.61 | G35: =F35*(1+G32) -> 64159.328 | H35: =G35*(1+H32) -> 66084.108
A36: NOI | B36: =B34-B35 -> 112751.6 | C36: =+C34-C35 -> 116134.15 | D36: =+D34-D35 -> 119618.17 | E36: =+E34-E35 -> 123206.72 | F36: =+F34-F35 -> 126902.92 | G36: =+G34-G35 -> 130710.01 | H36: =+H34-H35 -> 134631.31
A37: Other cash flow items (if required)
A38: Debts servicing | C38: =$C$72*12 -> -104183.62 | D38: =$C$72*12 -> -104183.62 | E38: =$C$72*12 -> -104183.62 | F38: =$C$72*12 -> -104183.62 | G38: =$C$72*12 -> -104183.62 | H38: =$C$72*12 -> -104183.62
A39: Cash flow | B39: =+B36-B37+B38 -> 112751.6 | C39: =+C36-C37+C38 -> 11950.531 | D39: =+D36-D37+D38 -> 15434.555 | E39: =+E36-E37+E38 -> 19023.1 | F39: =+F36-F37+F38 -> 22719.302 | G39: =+G36-G37+G38 -> 26526.389 | H39: =+H36-H37+H38 -> 30447.689
A44: UNLEVERED CASH FLOWS
B45: Initial | C45: Year 1 | D45: Year 2 | E45: Year 3 | F45: Year 4 | G45: Year 5
A46: Investment | B46: =-B8-B10 -> -2748900
A47: Cash flow | C47: =C39-C38 -> 116134.15 | D47: =D39-D38 -> 119618.17 | E47: =E39-E38 -> 123206.72 | F47: =F39-F38 -> 126902.92 | G47: =G39-G38 -> 130710.01
A48: Cash on exit | G48: =(H36/$B$21)*(1-B22) -> 2872134.5
B49: =SUM(B46:B48) -> -2748900 | C49: =SUM(C46:C48) -> 116134.15 | D49: =SUM(D46:D48) -> 119618.17 | E49: =SUM(E46:E48) -> 123206.72 | F49: =SUM(F46:F48) -> 126902.92 | G49: =SUM(G46:G48) -> 3002844.6
A52: IRR unlevered | B52: =IRR(B49:G49) -> 0.052791467
A53: NPV unlevered | B53: =NPV(B23,C49:G49)+B49 -> -85013.866
A57: LEVERED CASH FLOWS
B58: Initial | C58: Year 1 | D58: Year 2 | E58: Year 3 | F58: Year 4 | G58: Year 5
A59: Investment | B59: =-B8-B10 -> -2748900
A60: Cash flow | B60: =B12 -> 1617000 | C60: {=C39:G39} -> 11950.531 | D60: 15434.555 | E60: 19023.1 | F60: 22719.302 | G60: 26526.389
A61: Cash on exit | G61: =((H36/B21)*(1-B22))-F131 -> 1459609.4
B62: =SUM(B59:B61) -> -1131900 | C62: =SUM(C59:C61) -> 11950.531 | D62: =SUM(D59:D61) -> 15434.555 | E62: =SUM(E59:E61) -> 19023.1 | F62: =SUM(F59:F61) -> 22719.302 | G62: =SUM(G59:G61) -> 1486135.8
A65: IRR levered | B65: =IRR(B62:G62) -> 0.067119595
A66: NPV levered | B66: =NPV(B24,C62:G62)+B62 -> -97933.594
A70: DEBT AMORTIZATION SCHEDULE
A71: Payment | B71: Opening | C71: Payment | D71: Interest | E71: Capital | F71: Closing
A72: 1 | B72: =+B12 -> 1617000 | C72: =PMT($B$14,$B$15*12,B72,0) -> -8681.9681 | D72: =+B72*$B$14 -> 5610.6056 | E72: =+C72+D72 -> -3071.3625 | F72: =+B72+E72 -> 1613928.6
A73: =1+A72 -> 2 | B73: =F72 -> 1613928.6 | C73: =C72 -> -8681.9681 | D73: =+B73*$B$14 -> 5599.9487 | E73: =+C73+D73 -> -3082.0194 | F73: =+B73+E73 -> 1610846.6
A74: =1+A73 -> 3 | B74: =F73 -> 1610846.6 | C74: =C73 -> -8681.9681 | D74: =+B74*$B$14 -> 5589.2548 | E74: =+C74+D74 -> -3092.7133 | F74: =+B74+E74 -> 1607753.9
A75: =1+A74 -> 4 | B75: =F74 -> 1607753.9 | C75: =C74 -> -8681.9681 | D75: =+B75*$B$14 -> 5578.5238 | E75: =+C75+D75 -> -3103.4443 | F75: =+B75+E75 -> 1604650.5
A76: =1+A75 -> 5 | B76: =F75 -> 1604650.5 | C76: =C75 -> -8681.9681 | D76: =+B76*$B$14 -> 5567.7556 | E76: =+C76+D76 -> -3114.2125 | F76: =+B76+E76 -> 1601536.2
A77: =1+A76 -> 6 | B77: =F76 -> 1601536.2 | C77: =C76 -> -8681.9681 | D77: =+B77*$B$14 -> 5556.95 | E77: =+C77+D77 -> -3125.0181 | F77: =+B77+E77 -> 1598411.2
A78: =1+A77 -> 7 | B78: =F77 -> 1598411.2 | C78: =C77 -> -8681.9681 | D78: =+B78*$B$14 -> 5546.107 | E78: =+C78+D78 -> -3135.8611 | F78: =+B78+E78 -> 1595275.4
A79: =1+A78 -> 8 | B79: =F78 -> 1595275.4 | C79: =C78 -> -8681.9681 | D79: =+B79*$B$14 -> 5535.2263 | E79: =+C79+D79 -> -3146.7418 | F79: =+B79+E79 -> 1592128.6
A80: =1+A79 -> 9 | B80: =F79 -> 1592128.6 | C80: =C79 -> -8681.9681 | D80: =+B80*$B$14 -> 5524.3078 | E80: =+C80+D80 -> -3157.6603 | F80: =+B80+E80 -> 1588971
A81: =1+A80 -> 10 | B81: =F80 -> 1588971 | C81: =C80 -> -8681.9681 | D81: =+B81*$B$14 -> 5513.3515 | E81: =+C81+D81 -> -3168.6166 | F81: =+B81+E81 -> 1585802.3
A82: =1+A81 -> 11 | B82: =F81 -> 1585802.3 | C82: =C81 -> -8681.9681 | D82: =+B82*$B$14 -> 5502.3572 | E82: =+C82+D82 -> -3179.611 | F82: =+B82+E82 -> 1582622.7
A83: =1+A82 -> 12 | B83: =F82 -> 1582622.7 | C83: =C82 -> -8681.9681 | D83: =+B83*$B$14 -> 5491.3247 | E83: =+C83+D83 -> -3190.6435 | F83: =+B83+E83 -> 1579432.1
A84: =1+A83 -> 13 | B84: =F83 -> 1579432.1 | C84: =C83 -> -8681.9681 | D84: =+B84*$B$14 -> 5480.2539 | E84: =+C84+D84 -> -3201.7142 | F84: =+B84+E84 -> 1576230.4
... A371: =1+A370 -> 300 | B371: =F370 -> 8651.9479 | C371: =C370 -> -8681.9681 | D371: =+B371*$B$14 -> 30.020202 | E371: =+C371+D371 -> -8651.9479 | F371: =+B371+E371 -> 7.8398443e-10

Sheet Optimistic
A1: OPTIMISTIC SCENARIO
A3: DEAL PARAMETERS | D3: PRI | F3: =+$B$34 -> 168096
A4: Asset type | B4: Multi-Residential | D4: Vacancy + Credit allowance | F4: =1%*F3 -> 1680.96
A5: Asking Price | B5: 2685000 | D5: ERI | F5: =F3-F4 -> 166415.04
A6: NOI - Year 1 | B6: =+C36 -> 120940.42 | D6: Misc income | F6: 0
A7: Implied Cap rate | B7: =B6/B5 -> 0.045042987 | D7: GOI | F7: =F5 -> 166415.04
A8: Purchase Price | B8: 2675000 | D8: Operating expense | F8: =51142 -> 51142
A9: Cap rate | B9: =B6/B8 -> 0.045211372 | D9: NOI | F9: =F7-F8 -> 115273.04
A10: Acqusition expenses | B10: =0.02*B8 -> 53500
A11: Financing LTV | B11: 0.7
A12: Financing amount | B12: =B11*B8 -> 1872500
A13: Mortgage rate | B13: 0.035 | E13: Weight | F13: Cost | G13: WACC
A14: Mortgage monthly rate | B14: =NOMINAL(EFFECT(B13,2),12)/12 -> 0.002895624 | D14: Debt | E14: =B11 -> 0.7 | F14: =B13 -> 0.035
A15: Mortgage amortization period | B15: 25 | D15: Equity | E15: =1-E14 -> 0.3 | F15: 0.1284
A16: Equity funding after leverage | B16: =B8-B12+B10 -> 856000 | F16: =(E14*F14)+(E15*F15) -> 0.06302 | G16: =B21+0.02 -> 0.063
A17: Own Equity % | B17: 0.5
A18: Investor Equity % | B18: 0.5
A19: Own Equity funding after leverage | B19: =B17*B16 -> 428000
A20: Investor Equity funding after leverage | B20: =B18*B16 -> 428000
A21: Exit cap rate | B21: 0.043
A22: Sale expenses | B22: 0.04 | C22: Of sale price
A23: Investor unlevered hurdle rate | B23: =6.3% -> 0.063
A24: Investor levered hurdle rate | B24: =F15 -> 0.1284
A27: NOI AND CASH FLOW
B28: Actual | C28: Projected
B29: Last Year | C29: Year 1 | D29: Year 2 | E29: Year 3 | F29: Year 4 | G29: Year 5 | H29: Year 6
A31: Revenue growth percentage rate | C31: 0.04 | D31: 0.04 | E31: 0.04 | F31: 0.04 | G31: 0.04 | H31: 0.04
A32: Expense growth percentage rate | C32: 0.02 | D32: 0.02 | E32: 0.02 | F32: 0.02 | G32: 0.02 | H32: 0.02
A34: Revenues | B34: 168096 | C34: =B34*(1+C31) -> 174819.84 | D34: =C34*(1+D31) -> 181812.63 | E34: =D34*(1+E31) -> 189085.14 | F34: =E34*(1+F31) -> 196648.54 | G34: =F34*(1+G31) -> 204514.49 | H34: =G34*(1+H31) -> 212695.07
A35: Expenses | B35: =F4+F8 -> 52822.96 | C35: =B35*(1+C32) -> 53879.419 | D35: =C35*(1+D32) -> 54957.008 | E35: =D35*(1+E32) -> 56056.148 | F35: =E35*(1+F32) -> 57177.271 | G35: =F35*(1+G32) -> 58320.816 | H35: =G35*(1+H32) -> 59487.232
A36: NOI | B36: =B34-B35 -> 115273.04 | C36: =+C34-C35 -> 120940.42 | D36: =+D34-D35 -> 126855.63 | E36: =+E34-E35 -> 133028.99 | F36: =+F34-F35 -> 139471.27 | G36: =+G34-G35 -> 146193.67 | H36: =+H34-H35 -> 153207.83
A37: Other cash flow items (if required)
A38: Debts servicing | C38: =$C$72*12 -> -112186.04 | D38: =$C$72*12 -> -112186.04 | E38: =$C$72*12 -> -112186.04 | F38: =$C$72*12 -> -112186.04 | G38: =$C$72*12 -> -112186.04
A39: Cash flow | B39: =B36 -> 115273.04 | C39: =+C36-C37+C38 -> 8754.3771 | D39: =+D36-D37+D38 -> 14669.582 | E39: =+E36-E37+E38 -> 20842.948 | F39: =+F36-F37+F38 -> 27285.23 | G39: =+G36-G37+G38 -> 34007.626 | H39: =+H36-H37+H38 -> 153207.83
A44: UNLEVERED CASH FLOWS
B45: Initial | C45: Year 1 | D45: Year 2 | E45: Year 3 | F45: Year 4 | G45: Year 5
A46: Investment | B46: =-B8-B10 -> -2728500
A47: Cash flow | C47: =C39-C38 -> 120940.42 | D47: =D39-D38 -> 126855.63 | E47: =E39-E38 -> 133028.99 | F47: =F39-F38 -> 139471.27 | G47: =G39-G38 -> 146193.67
A48: Cash on exit | G48: =(H36/$B$21)*(1-B22) -> 3420454
B49: =SUM(B46:B48) -> -2728500 | C49: =SUM(C46:C48) -> 120940.42 | D49: =SUM(D46:D48) -> 126855.63 | E49: =SUM(E46:E48) -> 133028.99 | F49: =SUM(F46:F48) -> 139471.27 | G49: =SUM(G46:G48) -> 3566647.6
A52: IRR unlevered | B52: =IRR(B49:G49) -> 0.09076435
A53: NPV unlevered | B53: =NPV(B23,C49:G49)+B49 -> 345330.12
A57: LEVERED CASH FLOWS
B58: Initial | C58: Year 1 | D58: Year 2 | E58: Year 3 | F58: Year 4 | G58: Year 5
A59: Investment | B59: =-B8-B10 -> -2728500
A60: Cash flow | B60: =B12 -> 1872500 | C60: {=C39:G39} -> 8754.3771 | D60: 14669.582 | E60: 20842.948 | F60: 27285.23 | G60: 34007.626
A61: Cash on exit | G61: =((H39/B21)*(1-B22))-F131 -> 1804861.3
B62: =SUM(B59:B61) -> -856000 | C62: =SUM(C59:C61) -> 8754.3771 | D62: =SUM(D59:D61) -> 14669.582 | E62: =SUM(E59:E61) -> 20842.948 | F62: =SUM(F59:F61) -> 27285.23 | G62: =SUM(G59:G61) -> 1838868.9
A65: IRR levered | B65: =IRR(B62:G62) -> 0.17787468
A66: NPV levered | B66: =NPV(B24,C62:G62)+B62 -> 199776.09
A70: DEBT AMORTIZATION SCHEDULE
A71: Payment | B71: Opening | C71: Payment | D71: Interest | E71: Capital | F71: Closing
A72: 1 | B72: =+B12 -> 1872500 | C72: =PMT($B$14,$B$15*12,B72,0) -> -9348.837 | D72: =+B72*$B$14 -> 5422.0559 | E72: =+C72+D72 -> -3926.7811 | F72: =+B72+E72 -> 1868573.2
A73: =1+A72 -> 2 | B73: =F72 -> 1868573.2 | C73: =C72 -> -9348.837 | D73: =+B73*$B$14 -> 5410.6854 | E73: =+C73+D73 -> -3938.1516 | F73: =+B73+E73 -> 1864635.1
A74: =1+A73 -> 3 | B74: =F73 -> 1864635.1 | C74: =C73 -> -9348.837 | D74: =+B74*$B$14 -> 5399.282 | E74: =+C74+D74 -> -3949.555 | F74: =+B74+E74 -> 1860685.5
A75: =1+A74 -> 4 | B75: =F74 -> 1860685.5 | C75: =C74 -> -9348.837 | D75: =+B75*$B$14 -> 5387.8456 | E75: =+C75+D75 -> -3960.9914 | F75: =+B75+E75 -> 1856724.5
A76: =1+A75 -> 5 | B76: =F75 -> 1856724.5 | C76: =C75 -> -9348.837 | D76: =+B76*$B$14 -> 5376.376 | E76: =+C76+D76 -> -3972.461 | F76: =+B76+E76 -> 1852752.1
A77: =1+A76 -> 6 | B77: =F76 -> 1852752.1 | C77: =C76 -> -9348.837 | D77: =+B77*$B$14 -> 5364.8733 | E77: =+C77+D77 -> -3983.9637 | F77: =+B77+E77 -> 1848768.1
A78: =1+A77 -> 7 | B78: =F77 -> 1848768.1 | C78: =C77 -> -9348.837 | D78: =+B78*$B$14 -> 5353.3372 | E78: =+C78+D78 -> -3995.4998 | F78: =+B78+E78 -> 1844772.6
A79: =1+A78 -> 8 | B79: =F78 -> 1844772.6 | C79: =C78 -> -9348.837 | D79: =+B79*$B$14 -> 5341.7677 | E79: =+C79+D79 -> -4007.0692 | F79: =+B79+E79 -> 1840765.5
A80: =1+A79 -> 9 | B80: =F79 -> 1840765.5 | C80: =C79 -> -9348.837 | D80: =+B80*$B$14 -> 5330.1648 | E80: =+C80+D80 -> -4018.6722 | F80: =+B80+E80 -> 1836746.9
A81: =1+A80 -> 10 | B81: =F80 -> 1836746.9 | C81: =C80 -> -9348.837 | D81: =+B81*$B$14 -> 5318.5282 | E81: =+C81+D81 -> -4030.3088 | F81: =+B81+E81 -> 1832716.5
A82: =1+A81 -> 11 | B82: =F81 -> 1832716.5 | C82: =C81 -> -9348.837 | D82: =+B82*$B$14 -> 5306.858 | E82: =+C82+D82 -> -4041.979 | F82: =+B82+E82 -> 1828674.6
A83: =1+A82 -> 12 | B83: =F82 -> 1828674.6 | C83: =C82 -> -9348.837 | D83: =+B83*$B$14 -> 5295.1539 | E83: =+C83+D83 -> -4053.6831 | F83: =+B83+E83 -> 1824620.9
A84: =1+A83 -> 13 | B84: =F83 -> 1824620.9 | C84: =C83 -> -9348.837 | D84: =+B84*$B$14 -> 5283.416 | E84: =+C84+D84 -> -4065.421 | F84: =+B84+E84 -> 1820555.5
... A371: =1+A370 -> 300 | B371: =F370 -> 9321.8444 | C371: =C370 -> -9348.837 | D371: =+B371*$B$14 -> 26.992556 | E371: =+C371+D371 -> -9321.8444 | F371: =+B371+E371 -> 2.582965e-10
